tensorflow_image/__init__.py
tensorflow_image/ai.py
tensorflow_image/define.py
tensorflow_image/image_classification_ai.py
tensorflow_image/image_lib.py
tensorflow_image/image_multi_label_ai.py
tensorflow_image/image_regression_ai.py
tensorflow_image/make_pix2pix_image.py
tensorflow_image/pix2pix.py
tensorflow_image/tf_callback.py
tensorflow_image/tflib.py
tensorflow_image-1.6.0.dist-info/LICENSE
tensorflow_image-1.6.0.dist-info/METADATA
tensorflow_image-1.6.0.dist-info/WHEEL
tensorflow_image-1.6.0.dist-info/top_level.txt
tensorflow_image-1.6.0.dist-info/RECORD
