Metadata-Version: 2.1
Name: tensorflow-image
Version: 1.6.0
Summary: Can train and infer image-related AI
Home-page: https://github.com/nicoyou/TensorflowImageAi
Author: nicoyou
Author-email: nicoyou.info@gmail.com
License: MIT
Keywords: tensorflow-image tensorflow image ai nicoyou
Classifier: Programming Language :: Python
Classifier: Programming Language :: Python :: 3
Classifier: Programming Language :: Python :: 3 :: Only
Classifier: Programming Language :: Python :: 3.10
License-File: LICENSE
Requires-Dist: nlib3
Requires-Dist: tensorflow
Requires-Dist: numpy
Requires-Dist: tqdm
Requires-Dist: opencv-contrib-python
Requires-Dist: pillow
Requires-Dist: matplotlib
Requires-Dist: pandas
Requires-Dist: scipy
